{"skeleton":{"hash":"JD04Zu/mA/KezhNh77jic7IDbbY","spine":"3.8.75","x":-79.26,"y":-3.33,"width":159,"height":147,"images":"./milo/","audio":""},"bones":[{"name":"root"},{"name":"cuerpo","parent":"root","length":103.85,"rotation":89.67,"x":-0.85,"y":20.15},{"name":"ojo1","parent":"cuerpo","length":23.47,"rotation":75.16,"x":65.42,"y":14.28},{"name":"ojo-fondo1","parent":"cuerpo","length":25.75,"rotation":83.29,"x":51.02,"y":46.85},{"name":"ojo12","parent":"cuerpo","length":21.64,"rotation":64.09,"x":57.46,"y":50.38},{"name":"boca","parent":"cuerpo","length":24.74,"rotation":92.32,"x":19.56,"y":37.95},{"name":"ojo-fondo2 (1)","parent":"cuerpo","length":30.89,"rotation":93.88,"x":53.56,"y":3.74}],"slots":[{"name":"cuerpo","bone":"cuerpo","attachment":"cuerpo"},{"name":"ojo-fondo2 (1)","bone":"ojo-fondo2 (1)","attachment":"ojo-fondo2 (1)"},{"name":"ojo-fondo1","bone":"ojo-fondo1","attachment":"ojo-fondo1"},{"name":"boca","bone":"boca","attachment":"boca"},{"name":"ojo1","bone":"ojo1","attachment":"ojo1"},{"name":"ojo12","bone":"ojo12","attachment":"ojo12"}],"skins":[{"name":"default","attachments":{"ojo12":{"ojo12":{"type":"mesh","uvs":[1,1,0,1,0,0,1,0],"triangles":[1,2,3,1,3,0],"vertices":[-6.9,13.16,10.79,20.07,18.43,0.51,0.73,-6.4],"hull":4,"edges":[0,2,2,4,4,6,0,6],"width":19,"height":21}},"ojo-fondo1":{"ojo-fondo1":{"type":"mesh","uvs":[0.00486,0.55002,0.0273,0.79864,0.13205,0.9592,0.39576,0.97718,0.73056,1,0.99241,0.72613,1,0.19782,0.75301,0,0.30412,0,0.01982,0.19782,0,0.37392,0.49116,0.51895,0.49864,0.19782],"triangles":[12,8,7,12,7,6,9,8,12,12,10,9,11,10,12,0,10,11,6,11,12,5,11,6,1,0,11,3,2,1,11,3,1,11,4,3,5,4,11],"vertices":[25.43,2.84,24.46,12.51,21.4,18.66,14.26,19.1,5.19,19.65,-1.47,8.71,-0.91,-11.89,6.04,-19.35,18.16,-18.89,25.54,-10.9,25.82,-4.02,12.35,1.14,12.62,-11.38],"hull":11,"edges":[0,2,2,4,8,10,10,12,12,14,14,16,16,18,18,20,0,20,4,6,6,8,6,22,22,24],"width":27,"height":39}},"cuerpo":{"cuerpo":{"type":"mesh","uvs":[0.00354,0.73047,0.0564,0.85754,0.13864,0.94332,0.30899,1,0.54108,0.99855,0.73781,0.99733,0.9111,0.84484,1,0.71141,1,0.33018,0.85823,0.15228,0.7055,0.0252,0.60858,0,0.29431,0,0.17389,0.07921,0.08577,0.18087,0,0.36513,0.48228,0.5335],"triangles":[16,12,11,13,12,16,14,13,16,15,14,16,16,9,8,0,15,16,16,11,10,16,10,9,8,7,16,6,16,7,1,0,16,2,1,16,5,16,6,16,3,2,5,4,16,4,3,16],"vertices":[15.69,77.95,-2.94,69.43,-15.47,56.28,-23.65,29.15,-23.22,-7.75,-22.86,-39.03,-0.28,-66.45,19.41,-80.47,75.45,-80.15,101.47,-57.45,120.01,-33.06,123.63,-17.63,123.34,32.34,111.58,51.42,96.56,65.34,69.39,78.82,45.09,2],"hull":16,"edges":[0,2,2,4,4,6,10,12,12,14,14,16,16,18,18,20,20,22,22,24,24,26,26,28,28,30,0,30,6,8,8,10,8,32],"width":159,"height":147}},"boca":{"boca":{"type":"mesh","uvs":[0.00532,0.87533,1,1,1,0,0,0,0,0.96633],"triangles":[0,3,2,4,3,0,0,2,1],"vertices":[19.86,1.87,-18.09,3.94,-18.3,-2.05,19.68,-3.38,19.88,2.42],"hull":5,"edges":[0,2,2,4,4,6,6,8,0,8],"width":38,"height":6}},"ojo-fondo2 (1)":{"ojo-fondo2 (1)":{"x":15.12,"y":-0.2,"rotation":175.58,"width":31,"height":41}},"ojo1":{"ojo1":{"type":"mesh","uvs":[0,0.5341,0.00259,0.8169,0.1408,1,0.43849,1,0.82122,1,1,0.6654,1,0.1099,0.73617,0,0.23649,0,0,0.2008,0,0.3725,0.49164,0.4937],"triangles":[11,10,9,11,8,7,11,9,8,0,10,11,11,7,6,5,11,6,1,0,11,3,2,1,11,3,1,4,3,11,5,4,11],"vertices":[14.54,16.51,13.01,21.96,9.52,24.8,4.06,23.32,-2.96,21.42,-4.48,14.07,-1.58,3.35,3.84,2.54,13,5.03,16.29,10.08,15.39,13.39,5.74,13.29],"hull":11,"edges":[0,2,2,4,8,10,10,12,12,14,14,16,16,18,18,20,0,20,4,6,6,8,6,22],"width":19,"height":20}}}}],"animations":{"animation":{"bones":{"cuerpo":{"scale":[{},{"time":0.5,"x":1.102,"y":0.947},{"time":1}]}}},"blinkNormal":{"bones":{"ojo-fondo1":{"scale":[{},{"time":0.1333,"y":0.004},{"time":0.3}]},"ojo-fondo2 (1)":{"scale":[{},{"time":0.1333,"y":0.002},{"time":0.3}]}}},"blinkRetarded1":{"bones":{"ojo-fondo1":{"scale":[{},{"time":0.2333,"y":0.013},{"time":0.4}]},"ojo-fondo2 (1)":{"scale":[{},{"time":0.3333,"y":-0.006},{"time":0.5}]}}},"blinkWeird":{"bones":{"ojo-fondo2 (1)":{"scale":[{"x":1.003,"y":1.003},{"time":0.2,"x":1.003,"y":0.39}]},"ojo-fondo1":{"scale":[{},{"time":0.2,"y":0.405}]}}},"doubleBlink":{"bones":{"ojo-fondo1":{"scale":[{},{"time":0.1667,"y":0.004},{"time":0.3333,"curve":"stepped"},{"time":0.5},{"time":0.6333,"y":0.004},{"time":0.7667}]},"ojo-fondo2 (1)":{"scale":[{},{"time":0.1667,"y":0.002},{"time":0.3333,"curve":"stepped"},{"time":0.5},{"time":0.6333,"y":0.002},{"time":0.7667}]}}},"rodar":{"bones":{"cuerpo":{"rotate":[{"time":0.4333},{"time":0.6333,"angle":-178.67},{"time":0.7,"angle":69.96},{"time":0.8,"angle":-0.67},{"time":0.9}],"translate":[{"time":0.3},{"time":0.4667,"x":1.43,"y":247.2},{"time":0.5667,"x":1.45,"y":309.71},{"time":0.6667,"x":1.46,"y":333.37},{"time":0.7333,"x":1.47,"y":295.71},{"time":0.8333,"x":1.49,"y":252.46},{"time":0.9333,"x":1.51,"y":208.34},{"time":1.3333,"x":0.05,"y":8.1}],"scale":[{},{"time":0.1333,"x":0.819,"y":1.163},{"time":0.3,"x":1.343,"y":0.739},{"time":0.4667,"curve":"stepped"},{"time":0.9333},{"time":1.3333,"x":1.343,"y":0.739},{"time":1.6},{"time":1.7,"x":0.868,"y":1.141},{"time":1.9667}]},"ojo12":{"translate":[{"x":0.11,"y":-0.05},{"time":0.1333,"x":-4.63,"y":1.01},{"time":4.2667,"x":-4.62,"y":-0.41}]},"ojo1":{"translate":[{},{"time":0.1333,"x":-6.89,"y":-1.85}]}}}}}